nwmurl/__init__.py
nwmurl/urlgennwm.py
nwmurl/validation_util.py
nwmurl-1.0.5.dist-info/licenses/LICENSE.txt
nwmurl-1.0.5.dist-info/METADATA
nwmurl-1.0.5.dist-info/WHEEL
nwmurl-1.0.5.dist-info/top_level.txt
nwmurl-1.0.5.dist-info/RECORD
