Metadata-Version: 2.4
Name: nwmurl
Version: 1.0.5
Summary: URL generator tool for National Water Model data
Author: Sepehr Karimi (CIROH)
Author-email: mkarimiziarani@ua.edu
Keywords: python,NWM,url
Classifier: Development Status :: 1 - Planning
Classifier: Intended Audience :: Developers
Classifier: Programming Language :: Python :: 3
Classifier: Operating System :: Unix
Classifier: Operating System :: MacOS :: MacOS X
Classifier: Operating System :: Microsoft :: Windows
License-File: LICENSE.txt
Requires-Dist: setuptools
Requires-Dist: wheel
Requires-Dist: pytest
Requires-Dist: python-dateutil
Requires-Dist: requests
Requires-Dist: tqdm
Requires-Dist: gevent
Dynamic: author
Dynamic: author-email
Dynamic: classifier
Dynamic: description
Dynamic: description-content-type
Dynamic: keywords
Dynamic: license-file
Dynamic: requires-dist
Dynamic: summary
